README.md
setup.cfg
setup.py
xSG33.py
xinabox_SG33.egg-info/PKG-INFO
xinabox_SG33.egg-info/SOURCES.txt
xinabox_SG33.egg-info/dependency_links.txt
xinabox_SG33.egg-info/requires.txt
xinabox_SG33.egg-info/top_level.txt