Metadata-Version: 2.1
Name: xinabox-SG33
Version: 0.0.1
Summary: Indoor Air Quality Sensor
Home-page: https://github.com/xinabox/Python-SG33
Author: Luqmaan Baboo
Author-email: luqmaanbaboo@gmail.com
License: UNKNOWN
Platform: UNKNOWN
Classifier: Programming Language :: Python :: 3
Classifier: License :: OSI Approved :: MIT License
Classifier: Operating System :: OS Independent
Requires-Python: >=3.6
